dxe_airtable/airtable.py
dxe_airtable/airtable_to_mailing_list.py
dxe_airtable/generate_members_data.py
dxe_airtable/generate_chapter_data.py
dxe_airtable/__init__.py
dxe_airtable/backup_airtable.py
dxe_airtable/test_airtable_to_mailing_list.py
dxe_airtable-1.0.0.dist-info/METADATA
dxe_airtable-1.0.0.dist-info/top_level.txt
dxe_airtable-1.0.0.dist-info/DESCRIPTION.rst
dxe_airtable-1.0.0.dist-info/RECORD
dxe_airtable-1.0.0.dist-info/WHEEL
dxe_airtable-1.0.0.dist-info/metadata.json
