Metadata-Version: 2.0
Name: dxe-airtable
Version: 1.0.0
Summary: Add FontAwesome icons to StreamField.
Home-page: https://github.com/directactioneverywhere/dxe-airtable
Author: DxE Tech Working Group
Author-email: tech@directactioneverywhere.com
License: GPL-3.0
Keywords: development
Platform: UNKNOWN
Classifier: Environment :: Web Environment
Classifier: Intended Audience :: Developers
Classifier: Operating System :: OS Independent
Classifier: Programming Language :: Python
Classifier: Topic :: Internet :: WWW/HTTP
Classifier: Topic :: Internet :: WWW/HTTP :: Dynamic Content
Requires-Dist: requests
